qixo/__init__.py
qixo/core.py
qixo-0.1.1.dist-info/licenses/LICENSE
qixo-0.1.1.dist-info/METADATA
qixo-0.1.1.dist-info/WHEEL
qixo-0.1.1.dist-info/top_level.txt
qixo-0.1.1.dist-info/RECORD
