Metadata-Version: 2.4
Name: qixo
Version: 0.1.1
Summary: A lightweight Python library for executing JavaScript in a QuickJS sandbox
Author-email: "Jeorge D. Anderson II" <jeorge@jeorgeanderson.com>
License: Apache-2.0
Project-URL: Homepage, https://github.com/jeorgexyz/qixo
Project-URL: Repository, https://github.com/jeorgexyz/qixo
Project-URL: Issues, https://github.com/jeorgexyz/qixo/issues
Classifier: Development Status :: 3 - Alpha
Classifier: Intended Audience :: Developers
Classifier: License :: OSI Approved :: Apache Software License
Classifier: Programming Language :: Python :: 3
Classifier: Programming Language :: Python :: 3.10
Classifier: Programming Language :: Python :: 3.11
Classifier: Programming Language :: Python :: 3.12
Requires-Python: >=3.10
License-File: LICENSE
Requires-Dist: quickjs>=1.19.2
Provides-Extra: dev
Requires-Dist: pytest>=7.0.0; extra == "dev"
Requires-Dist: pytest-cov>=4.0.0; extra == "dev"
Requires-Dist: black>=23.0.0; extra == "dev"
Requires-Dist: ruff>=0.1.0; extra == "dev"
Dynamic: license-file
